pdfjinja.py
pdfjinja-1.0.0.dist-info/DESCRIPTION.rst
pdfjinja-1.0.0.dist-info/entry_points.txt
pdfjinja-1.0.0.dist-info/METADATA
pdfjinja-1.0.0.dist-info/metadata.json
pdfjinja-1.0.0.dist-info/RECORD
pdfjinja-1.0.0.dist-info/top_level.txt
pdfjinja-1.0.0.dist-info/WHEEL
