Metadata-Version: 2.0
Name: pdfjinja
Version: 1.0.0
Summary: Use jinja templates to fill and sign pdf forms.
Home-page: http://github.com/rammie/pdfjinja/
Author: Ram Mehta
Author-email: ram.mehta@gmail.com
License: UNKNOWN
Platform: UNKNOWN
Requires-Dist: fdfgen (>=0.13.0)
Requires-Dist: jinja2 (>=2.8)
Requires-Dist: pdfminer.six (==20160202)
Requires-Dist: Pillow (>=3.2.0)
Requires-Dist: PyPDF2 (>=1.25.1)
Requires-Dist: reportlab (>=3.3.0)
